{
    "Home":"Ana Sayfa",
    "Swap":"Takas",
    "Perps":"Perps",
    "Affiliate":"Ortak",
    "Competitions":"Yarışmalar",
    "Fair Launch":"Adil Başlangıç",
    "Buy XDOGE":"XDOGE Satın Al",
    "How To Buy":"Nasıl Satın Alınır",
    "AirDrop":"Hava Bırakma",
    "Tokenomics":"Token Ekonomisi",
    "WhitePaper":"Beyaz Kağıt",
    "Farm":"Çiftlik",
    "Bridge":"Köprü",
    "Audit":"Denetim",
    "Docs":"Belgeler",
    "Connect Wallet":"Bağla",
    "Connect a Wallet":"Cüzdan Bağla",
    "Logout":"Çıkış Yap",
    "Select a Network":"Bir Ağ Seç",
    "Wrong Network":"Yanlış Ağ",
    "Base":"Base",
    "Base Goerli Test":"Base Goerli Test",
    "XDOGE Swap-Share liquidity with Uniswap!":"XDOGE Swap - Uniswap ile likidite paylaşın!",    
    "Copyright © 2023-2025 XDOGE Token":"Telif Hakkı © 2023-2025 XDOGE Token",
    "CONTACT":"İLETİŞİM"
}